skopt/__init__.py
skopt/acquisition.py
skopt/benchmarks.py
skopt/callbacks.py
skopt/plots.py
skopt/searchcv.py
skopt/utils.py
skopt/ext/__init__.py
skopt/ext/weighted_validation.py
skopt/learning/__init__.py
skopt/learning/forest.py
skopt/learning/gbrt.py
skopt/learning/gaussian_process/__init__.py
skopt/learning/gaussian_process/gpr.py
skopt/learning/gaussian_process/kernels.py
skopt/optimizer/__init__.py
skopt/optimizer/base.py
skopt/optimizer/dummy.py
skopt/optimizer/forest.py
skopt/optimizer/gbrt.py
skopt/optimizer/gp.py
skopt/optimizer/optimizer.py
skopt/sampler/__init__.py
skopt/sampler/base.py
skopt/sampler/grid.py
skopt/sampler/halton.py
skopt/sampler/hammersly.py
skopt/sampler/lhs.py
skopt/sampler/sobol.py
skopt/space/__init__.py
skopt/space/space.py
skopt/space/transformers.py
scikit_optimize_w-2020.2.dist-info/AUTHORS.md
scikit_optimize_w-2020.2.dist-info/LICENSE
scikit_optimize_w-2020.2.dist-info/METADATA
scikit_optimize_w-2020.2.dist-info/WHEEL
scikit_optimize_w-2020.2.dist-info/top_level.txt
scikit_optimize_w-2020.2.dist-info/RECORD
