Metadata-Version: 2.1
Name: scikit-optimize-w
Version: 2020.2
Summary: Sequential model-based optimization toolbox.
Home-page: https://github.com/mimba/scikit-optimize
Author: The scikit-optimize contributors
License: BSD 3-clause
Platform: UNKNOWN
Classifier: Intended Audience :: Science/Research
Classifier: Intended Audience :: Developers
Classifier: License :: OSI Approved :: BSD License
Classifier: Programming Language :: Python
Classifier: Topic :: Software Development
Classifier: Topic :: Scientific/Engineering
Classifier: Operating System :: Microsoft :: Windows
Classifier: Operating System :: POSIX
Classifier: Operating System :: Unix
Classifier: Operating System :: MacOS
Classifier: Programming Language :: Python :: 3.5
Classifier: Programming Language :: Python :: 3.6
Classifier: Programming Language :: Python :: 3.7
Classifier: Programming Language :: Python :: 3.8
Requires-Dist: joblib (>=0.14.1)
Requires-Dist: pyaml (>=20.4.0)
Requires-Dist: numpy (>=1.18.3)
Requires-Dist: scipy (>=1.4.1)
Requires-Dist: scikit-learn (>=0.22.2.post1)
Provides-Extra: plots
Requires-Dist: matplotlib (>=3.2.1) ; extra == 'plots'
